{
    "artifacts": {
        "archaicpetra": "Archaic Petra",
        "Archaic Petra": "archaicpetra",
        "berserker": "Berserker",
        "Berserker": "berserker",
        "blizzardstrayer": "Blizzard Strayer",
        "Blizzard Strayer": "blizzardstrayer",
        "bloodstainedchivalry": "Bloodstained Chivalry",
        "Bloodstained Chivalry": "bloodstainedchivalry",
        "braveheart": "Brave Heart",
        "Brave Heart": "braveheart",
        "crimsonwitchofflames": "Crimson Witch of Flames",
        "Crimson Witch of Flames": "crimsonwitchofflames",
        "deepwoodmemories": "Deepwood Memories",
        "Deepwood Memories": "deepwoodmemories",
        "defenderswill": "Defender's Will",
        "Defender's Will": "defenderswill",
        "desertpavilionchronicle": "Desert Pavilion Chronicle",
        "Desert Pavilion Chronicle": "desertpavilionchronicle",
        "echoesofanoffering": "Echoes of an Offering",
        "Echoes of an Offering": "echoesofanoffering",
        "emblemofseveredfate": "Emblem of Severed Fate",
        "Emblem of Severed Fate": "emblemofseveredfate",
        "finaleofthedeepgalleries": "Finale of the Deep Galleries",
        "Finale of the Deep Galleries": "finaleofthedeepgalleries",
        "flowerofparadiselost": "Flower of Paradise Lost",
        "Flower of Paradise Lost": "flowerofparadiselost",
        "fragmentofharmonicwhimsy": "Fragment of Harmonic Whimsy",
        "Fragment of Harmonic Whimsy": "fragmentofharmonicwhimsy",
        "gambler": "Gambler",
        "Gambler": "gambler",
        "gildeddreams": "Gilded Dreams",
        "Gilded Dreams": "gildeddreams",
        "gladiatorsfinale": "Gladiator's Finale",
        "Gladiator's Finale": "gladiatorsfinale",
        "goldentroupe": "Golden Troupe",
        "Golden Troupe": "goldentroupe",
        "heartofdepth": "Heart of Depth",
        "Heart of Depth": "heartofdepth",
        "huskofopulentdreams": "Husk of Opulent Dreams",
        "Husk of Opulent Dreams": "huskofopulentdreams",
        "instructor": "Instructor",
        "Instructor": "instructor",
        "lavawalker": "Lavawalker",
        "Lavawalker": "lavawalker",
        "longnightsoath": "Long Night's Oath",
        "Long Night's Oath": "longnightsoath",
        "maidenbeloved": "Maiden Beloved",
        "Maiden Beloved": "maidenbeloved",
        "marechausseehunter": "Marechaussee Hunter",
        "Marechaussee Hunter": "marechausseehunter",
        "martialartist": "Martial Artist",
        "Martial Artist": "martialartist",
        "nighttimewhispersintheechoingwoods": "Nighttime Whispers in the Echoing Woods",
        "Nighttime Whispers in the Echoing Woods": "nighttimewhispersintheechoingwoods",
        "noblesseoblige": "Noblesse Oblige",
        "Noblesse Oblige": "noblesseoblige",
        "nymphsdream": "Nymph's Dream",
        "Nymph's Dream": "nymphsdream",
        "obsidiancodex": "Obsidian Codex",
        "Obsidian Codex": "obsidiancodex",
        "oceanhuedclam": "Ocean-Hued Clam",
        "Ocean-Hued Clam": "oceanhuedclam",
        "paleflame": "Pale Flame",
        "Pale Flame": "paleflame",
        "resolutionofsojourner": "Resolution of Sojourner",
        "Resolution of Sojourner": "resolutionofsojourner",
        "retracingbolide": "Retracing Bolide",
        "Retracing Bolide": "retracingbolide",
        "scholar": "Scholar",
        "Scholar": "scholar",
        "scrolloftheheroofcindercity": "Scroll of the Hero of Cinder City",
        "Scroll of the Hero of Cinder City": "scrolloftheheroofcindercity",
        "shimenawasreminiscence": "Shimenawa's Reminiscence",
        "Shimenawa's Reminiscence": "shimenawasreminiscence",
        "songofdayspast": "Song of Days Past",
        "Song of Days Past": "songofdayspast",
        "tenacityofthemillelith": "Tenacity of the Millelith",
        "Tenacity of the Millelith": "tenacityofthemillelith",
        "theexile": "The Exile",
        "The Exile": "theexile",
        "thunderingfury": "Thundering Fury",
        "Thundering Fury": "thunderingfury",
        "thundersoother": "Thundersoother",
        "Thundersoother": "thundersoother",
        "unfinishedreverie": "Unfinished Reverie",
        "Unfinished Reverie": "unfinishedreverie",
        "vermillionhereafter": "Vermillion Hereafter",
        "Vermillion Hereafter": "vermillionhereafter",
        "viridescentvenerer": "Viridescent Venerer",
        "Viridescent Venerer": "viridescentvenerer",
        "vourukashasglow": "Vourukasha's Glow",
        "Vourukasha's Glow": "vourukashasglow",
        "wandererstroupe": "Wanderer's Troupe",
        "Wanderer's Troupe": "wandererstroupe"
    },
    "weapons": {
        "absolution": "Absolution",
        "Absolution": "absolution",
        "akuoumaru": "Akuoumaru",
        "Akuoumaru": "akuoumaru",
        "alleyhunter": "Alley Hunter",
        "Alley Hunter": "alleyhunter",
        "amenomakageuchi": "Amenoma Kageuchi",
        "Amenoma Kageuchi": "amenomakageuchi",
        "amosbow": "Amos' Bow",
        "Amos' Bow": "amosbow",
        "apprenticesnotes": "Apprentice's Notes",
        "Apprentice's Notes": "apprenticesnotes",
        "aquasimulacra": "Aqua Simulacra",
        "Aqua Simulacra": "aquasimulacra",
        "aquilafavonia": "Aquila Favonia",
        "Aquila Favonia": "aquilafavonia",
        "ashgravendrinkinghorn": "Ash-Graven Drinking Horn",
        "Ash-Graven Drinking Horn": "ashgravendrinkinghorn",
        "astralvulturescrimsonplumage": "Astral Vulture's Crimson Plumage",
        "Astral Vulture's Crimson Plumage": "astralvulturescrimsonplumage",
        "athousandblazingsuns": "A Thousand Blazing Suns",
        "A Thousand Blazing Suns": "athousandblazingsuns",
        "athousandfloatingdreams": "A Thousand Floating Dreams",
        "A Thousand Floating Dreams": "athousandfloatingdreams",
        "azurelight": "Azurelight",
        "Azurelight": "azurelight",
        "balladoftheboundlessblue": "Ballad of the Boundless Blue",
        "Ballad of the Boundless Blue": "balladoftheboundlessblue",
        "balladofthefjords": "Ballad of the Fjords",
        "Ballad of the Fjords": "balladofthefjords",
        "beaconofthereedsea": "Beacon of the Reed Sea",
        "Beacon of the Reed Sea": "beaconofthereedsea",
        "beginnersprotector": "Beginner's Protector",
        "Beginner's Protector": "beginnersprotector",
        "blackcliffagate": "Blackcliff Agate",
        "Blackcliff Agate": "blackcliffagate",
        "blackclifflongsword": "Blackcliff Longsword",
        "Blackcliff Longsword": "blackclifflongsword",
        "blackcliffpole": "Blackcliff Pole",
        "Blackcliff Pole": "blackcliffpole",
        "blackcliffslasher": "Blackcliff Slasher",
        "Blackcliff Slasher": "blackcliffslasher",
        "blackcliffwarbow": "Blackcliff Warbow",
        "Blackcliff Warbow": "blackcliffwarbow",
        "blacktassel": "Black Tassel",
        "Black Tassel": "blacktassel",
        "bloodtaintedgreatsword": "Bloodtainted Greatsword",
        "Bloodtainted Greatsword": "bloodtaintedgreatsword",
        "calamityofeshu": "Calamity of Eshu",
        "Calamity of Eshu": "calamityofeshu",
        "calamityqueller": "Calamity Queller",
        "Calamity Queller": "calamityqueller",
        "cashflowsupervision": "Cashflow Supervision",
        "Cashflow Supervision": "cashflowsupervision",
        "chainbreaker": "Chain Breaker",
        "Chain Breaker": "chainbreaker",
        "cinnabarspindle": "Cinnabar Spindle",
        "Cinnabar Spindle": "cinnabarspindle",
        "cloudforged": "Cloudforged",
        "Cloudforged": "cloudforged",
        "compoundbow": "Compound Bow",
        "Compound Bow": "compoundbow",
        "coolsteel": "Cool Steel",
        "Cool Steel": "coolsteel",
        "cranesechoingcall": "Crane's Echoing Call",
        "Crane's Echoing Call": "cranesechoingcall",
        "crescentpike": "Crescent Pike",
        "Crescent Pike": "crescentpike",
        "crimsonmoonssemblance": "Crimson Moon's Semblance",
        "Crimson Moon's Semblance": "crimsonmoonssemblance",
        "darkironsword": "Dark Iron Sword",
        "Dark Iron Sword": "darkironsword",
        "dawningfrost": "Dawning Frost",
        "Dawning Frost": "dawningfrost",
        "deathmatch": "Deathmatch",
        "Deathmatch": "deathmatch",
        "debateclub": "Debate Club",
        "Debate Club": "debateclub",
        "dialoguesofthedesertsages": "Dialogues of the Desert Sages",
        "Dialogues of the Desert Sages": "dialoguesofthedesertsages",
        "dodocotales": "Dodoco Tales",
        "Dodoco Tales": "dodocotales",
        "dragonsbane": "Dragon's Bane",
        "Dragon's Bane": "dragonsbane",
        "dragonspinespear": "Dragonspine Spear",
        "Dragonspine Spear": "dragonspinespear",
        "dullblade": "Dull Blade",
        "Dull Blade": "dullblade",
        "earthshaker": "Earth Shaker",
        "Earth Shaker": "earthshaker",
        "elegyfortheend": "Elegy for the End",
        "Elegy for the End": "elegyfortheend",
        "emeraldorb": "Emerald Orb",
        "Emerald Orb": "emeraldorb",
        "endoftheline": "End of the Line",
        "End of the Line": "endoftheline",
        "engulfinglightning": "Engulfing Lightning",
        "Engulfing Lightning": "engulfinglightning",
        "etherlightspindlelute": "Etherlight Spindlelute",
        "Etherlight Spindlelute": "etherlightspindlelute",
        "everlastingmoonglow": "Everlasting Moonglow",
        "Everlasting Moonglow": "everlastingmoonglow",
        "eyeofperception": "Eye of Perception",
        "Eye of Perception": "eyeofperception",
        "fadingtwilight": "Fading Twilight",
        "Fading Twilight": "fadingtwilight",
        "fangofthemountainking": "Fang of the Mountain King",
        "Fang of the Mountain King": "fangofthemountainking",
        "favoniuscodex": "Favonius Codex",
        "Favonius Codex": "favoniuscodex",
        "favoniusgreatsword": "Favonius Greatsword",
        "Favonius Greatsword": "favoniusgreatsword",
        "favoniuslance": "Favonius Lance",
        "Favonius Lance": "favoniuslance",
        "favoniussword": "Favonius Sword",
        "Favonius Sword": "favoniussword",
        "favoniuswarbow": "Favonius Warbow",
        "Favonius Warbow": "favoniuswarbow",
        "ferrousshadow": "Ferrous Shadow",
        "Ferrous Shadow": "ferrousshadow",
        "festeringdesire": "Festering Desire",
        "Festering Desire": "festeringdesire",
        "filletblade": "Fillet Blade",
        "Fillet Blade": "filletblade",
        "finaleofthedeep": "Finale of the Deep",
        "Finale of the Deep": "finaleofthedeep",
        "fleuvecendreferryman": "Fleuve Cendre Ferryman",
        "Fleuve Cendre Ferryman": "fleuvecendreferryman",
        "flowerwreathedfeathers": "Flower-Wreathed Feathers",
        "Flower-Wreathed Feathers": "flowerwreathedfeathers",
        "flowingpurity": "Flowing Purity",
        "Flowing Purity": "flowingpurity",
        "fluteofezpitzal": "Flute of Ezpitzal",
        "Flute of Ezpitzal": "fluteofezpitzal",
        "footprintoftherainbow": "Footprint of the Rainbow",
        "Footprint of the Rainbow": "footprintoftherainbow",
        "forestregalia": "Forest Regalia",
        "Forest Regalia": "forestregalia",
        "freedomsworn": "Freedom-Sworn",
        "Freedom-Sworn": "freedomsworn",
        "frostbearer": "Frostbearer",
        "Frostbearer": "frostbearer",
        "fruitfulhook": "Fruitful Hook",
        "Fruitful Hook": "fruitfulhook",
        "fruitoffulfillment": "Fruit of Fulfillment",
        "Fruit of Fulfillment": "fruitoffulfillment",
        "hakushinring": "Hakushin Ring",
        "Hakushin Ring": "hakushinring",
        "halberd": "Halberd",
        "Halberd": "halberd",
        "hamayumi": "Hamayumi",
        "Hamayumi": "hamayumi",
        "harangeppakufutsu": "Haran Geppaku Futsu",
        "Haran Geppaku Futsu": "harangeppakufutsu",
        "harbingerofdawn": "Harbinger of Dawn",
        "Harbinger of Dawn": "harbingerofdawn",
        "heartstrings": "Silvershower Heartstrings",
        "Silvershower Heartstrings": "heartstrings",
        "huntersbow": "Hunter's Bow",
        "Hunter's Bow": "huntersbow",
        "hunterspath": "Hunter's Path",
        "Hunter's Path": "hunterspath",
        "ibispiercer": "Ibis Piercer",
        "Ibis Piercer": "ibispiercer",
        "ironpoint": "Iron Point",
        "Iron Point": "ironpoint",
        "ironsting": "Iron Sting",
        "Iron Sting": "ironsting",
        "jadefallssplendor": "Jadefall's Splendor",
        "Jadefall's Splendor": "jadefallssplendor",
        "kagotsurubeisshin": "Kagotsurube Isshin",
        "Kagotsurube Isshin": "kagotsurubeisshin",
        "kagurasverity": "Kagura's Verity",
        "Kagura's Verity": "kagurasverity",
        "katsuragikirinagamasa": "Katsuragikiri Nagamasa",
        "Katsuragikiri Nagamasa": "katsuragikirinagamasa",
        "keyofkhajnisut": "Key of Khaj-Nisut",
        "Key of Khaj-Nisut": "keyofkhajnisut",
        "kingssquire": "King's Squire",
        "King's Squire": "kingssquire",
        "kitaincrossspear": "Kitain Cross Spear",
        "Kitain Cross Spear": "kitaincrossspear",
        "lightoffoliarincision": "Light of Foliar Incision",
        "Light of Foliar Incision": "lightoffoliarincision",
        "lionsroar": "Lion's Roar",
        "Lion's Roar": "lionsroar",
        "lithicblade": "Lithic Blade",
        "Lithic Blade": "lithicblade",
        "lithicspear": "Lithic Spear",
        "Lithic Spear": "lithicspear",
        "lostprayertothesacredwinds": "Lost Prayer to the Sacred Winds",
        "Lost Prayer to the Sacred Winds": "lostprayertothesacredwinds",
        "lumidouceelegy": "Lumidouce Elegy",
        "Lumidouce Elegy": "lumidouceelegy",
        "luxurioussealord": "Luxurious Sea-Lord",
        "Luxurious Sea-Lord": "luxurioussealord",
        "magicguide": "Magic Guide",
        "Magic Guide": "magicguide",
        "mailedflower": "Mailed Flower",
        "Mailed Flower": "mailedflower",
        "makhairaaquamarine": "Makhaira Aquamarine",
        "Makhaira Aquamarine": "makhairaaquamarine",
        "mappamare": "Mappa Mare",
        "Mappa Mare": "mappamare",
        "memoryofdust": "Memory of Dust",
        "Memory of Dust": "memoryofdust",
        "messenger": "Messenger",
        "Messenger": "messenger",
        "missivewindspear": "Missive Windspear",
        "Missive Windspear": "missivewindspear",
        "mistsplitterreforged": "Mistsplitter Reforged",
        "Mistsplitter Reforged": "mistsplitterreforged",
        "mitternachtswaltz": "Mitternachts Waltz",
        "Mitternachts Waltz": "mitternachtswaltz",
        "moonpiercer": "Moonpiercer",
        "Moonpiercer": "moonpiercer",
        "moonweaversdawn": "Moonweaver's Dawn",
        "Moonweaver's Dawn": "moonweaversdawn",
        "mountainbracingbolt": "Mountain-Bracing Bolt",
        "Mountain-Bracing Bolt": "mountainbracingbolt",
        "mouunsmoon": "Mouun's Moon",
        "Mouun's Moon": "mouunsmoon",
        "oathsworneye": "Oathsworn Eye",
        "Oathsworn Eye": "oathsworneye",
        "oldmercspal": "Old Merc's Pal",
        "Old Merc's Pal": "oldmercspal",
        "otherworldlystory": "Otherworldly Story",
        "Otherworldly Story": "otherworldlystory",
        "peakpatrolsong": "Peak Patrol Song",
        "Peak Patrol Song": "peakpatrolsong",
        "pocketgrimoire": "Pocket Grimoire",
        "Pocket Grimoire": "pocketgrimoire",
        "polarstar": "Polar Star",
        "Polar Star": "polarstar",
        "portablepowersaw": "Portable Power Saw",
        "Portable Power Saw": "portablepowersaw",
        "predator": "Predator",
        "Predator": "predator",
        "primordialjadecutter": "Primordial Jade Cutter",
        "Primordial Jade Cutter": "primordialjadecutter",
        "primordialjadewingedspear": "Primordial Jade Winged-Spear",
        "Primordial Jade Winged-Spear": "primordialjadewingedspear",
        "prospectorsdrill": "Prospector's Drill",
        "Prospector's Drill": "prospectorsdrill",
        "prototypeamber": "Prototype Amber",
        "Prototype Amber": "prototypeamber",
        "prototypearchaic": "Prototype Archaic",
        "Prototype Archaic": "prototypearchaic",
        "prototypecrescent": "Prototype Crescent",
        "Prototype Crescent": "prototypecrescent",
        "prototyperancour": "Prototype Rancour",
        "Prototype Rancour": "prototyperancour",
        "prototypestarglitter": "Prototype Starglitter",
        "Prototype Starglitter": "prototypestarglitter",
        "rainslasher": "Rainslasher",
        "Rainslasher": "rainslasher",
        "rangegauge": "Range Gauge",
        "Range Gauge": "rangegauge",
        "ravenbow": "Raven Bow",
        "Raven Bow": "ravenbow",
        "recurvebow": "Recurve Bow",
        "Recurve Bow": "recurvebow",
        "redhornstonethresher": "Redhorn Stonethresher",
        "Redhorn Stonethresher": "redhornstonethresher",
        "rightfulreward": "Rightful Reward",
        "Rightful Reward": "rightfulreward",
        "ringofyaxche": "Ring of Yaxche",
        "Ring of Yaxche": "ringofyaxche",
        "royalbow": "Royal Bow",
        "Royal Bow": "royalbow",
        "royalgreatsword": "Royal Greatsword",
        "Royal Greatsword": "royalgreatsword",
        "royalgrimoire": "Royal Grimoire",
        "Royal Grimoire": "royalgrimoire",
        "royallongsword": "Royal Longsword",
        "Royal Longsword": "royallongsword",
        "royalspear": "Royal Spear",
        "Royal Spear": "royalspear",
        "rust": "Rust",
        "Rust": "rust",
        "sacrificersstaff": "Sacrificer's Staff",
        "Sacrificer's Staff": "sacrificersstaff",
        "sacrificialbow": "Sacrificial Bow",
        "Sacrificial Bow": "sacrificialbow",
        "sacrificialfragments": "Sacrificial Fragments",
        "Sacrificial Fragments": "sacrificialfragments",
        "sacrificialgreatsword": "Sacrificial Greatsword",
        "Sacrificial Greatsword": "sacrificialgreatsword",
        "sacrificialjade": "Sacrificial Jade",
        "Sacrificial Jade": "sacrificialjade",
        "sacrificialsword": "Sacrificial Sword",
        "Sacrificial Sword": "sacrificialsword",
        "sapwoodblade": "Sapwood Blade",
        "Sapwood Blade": "sapwoodblade",
        "scionoftheblazingsun": "Scion of the Blazing Sun",
        "Scion of the Blazing Sun": "scionoftheblazingsun",
        "seasonedhuntersbow": "Seasoned Hunter's Bow",
        "Seasoned Hunter's Bow": "seasonedhuntersbow",
        "sequenceofsolitude": "Sequence of Solitude",
        "Sequence of Solitude": "sequenceofsolitude",
        "serpentspine": "Serpent Spine",
        "Serpent Spine": "serpentspine",
        "sharpshootersoath": "Sharpshooter's Oath",
        "Sharpshooter's Oath": "sharpshootersoath",
        "silversword": "Silver Sword",
        "Silver Sword": "silversword",
        "skyridergreatsword": "Skyrider Greatsword",
        "Skyrider Greatsword": "skyridergreatsword",
        "skyridersword": "Skyrider Sword",
        "Skyrider Sword": "skyridersword",
        "skywardatlas": "Skyward Atlas",
        "Skyward Atlas": "skywardatlas",
        "skywardblade": "Skyward Blade",
        "Skyward Blade": "skywardblade",
        "skywardharp": "Skyward Harp",
        "Skyward Harp": "skywardharp",
        "skywardpride": "Skyward Pride",
        "Skyward Pride": "skywardpride",
        "skywardspine": "Skyward Spine",
        "Skyward Spine": "skywardspine",
        "slingshot": "Slingshot",
        "Slingshot": "slingshot",
        "snowtombedstarsilver": "Snow-Tombed Starsilver",
        "Snow-Tombed Starsilver": "snowtombedstarsilver",
        "solarpearl": "Solar Pearl",
        "Solar Pearl": "solarpearl",
        "songofbrokenpines": "Song of Broken Pines",
        "Song of Broken Pines": "songofbrokenpines",
        "songofstillness": "Song of Stillness",
        "Song of Stillness": "songofstillness",
        "splendoroftranquilwaters": "Splendor of Tranquil Waters",
        "Splendor of Tranquil Waters": "splendoroftranquilwaters",
        "staffofhoma": "Staff of Homa",
        "Staff of Homa": "staffofhoma",
        "staffofthescarletsands": "Staff of the Scarlet Sands",
        "Staff of the Scarlet Sands": "staffofthescarletsands",
        "starcallerswatch": "Starcaller's Watch",
        "Starcaller's Watch": "starcallerswatch",
        "sturdybone": "Sturdy Bone",
        "Sturdy Bone": "sturdybone",
        "summitshaper": "Summit Shaper",
        "Summit Shaper": "summitshaper",
        "sunnymorning": "Sunny Morning Sleep-In",
        "Sunny Morning Sleep-In": "sunnymorning",
        "surfsup": "Surf's Up",
        "Surf's Up": "surfsup",
        "swordofdescension": "Sword of Descension",
        "Sword of Descension": "swordofdescension",
        "swordofnarzissenkreuz": "Sword of Narzissenkreuz",
        "Sword of Narzissenkreuz": "swordofnarzissenkreuz",
        "symphonistofscents": "Symphonist of Scents",
        "Symphonist of Scents": "symphonistofscents",
        "talkingstick": "Talking Stick",
        "Talking Stick": "talkingstick",
        "tamayurateinoohanashi": "Tamayuratei no Ohanashi",
        "Tamayuratei no Ohanashi": "tamayurateinoohanashi",
        "thealleyflash": "The Alley Flash",
        "The Alley Flash": "thealleyflash",
        "thebell": "The Bell",
        "The Bell": "thebell",
        "theblacksword": "The Black Sword",
        "The Black Sword": "theblacksword",
        "thecatch": "\"The Catch\"",
        "\"The Catch\"": "thecatch",
        "thedockhandsassistant": "The Dockhand's Assistant",
        "The Dockhand's Assistant": "thedockhandsassistant",
        "thefirstgreatmagic": "The First Great Magic",
        "The First Great Magic": "thefirstgreatmagic",
        "theflute": "The Flute",
        "The Flute": "theflute",
        "thestringless": "The Stringless",
        "The Stringless": "thestringless",
        "theunforged": "The Unforged",
        "The Unforged": "theunforged",
        "theviridescenthunt": "The Viridescent Hunt",
        "The Viridescent Hunt": "theviridescenthunt",
        "thewidsith": "The Widsith",
        "The Widsith": "thewidsith",
        "thrillingtalesofdragonslayers": "Thrilling Tales of Dragon Slayers",
        "Thrilling Tales of Dragon Slayers": "thrillingtalesofdragonslayers",
        "thunderingpulse": "Thundering Pulse",
        "Thundering Pulse": "thunderingpulse",
        "tidalshadow": "Tidal Shadow",
        "Tidal Shadow": "tidalshadow",
        "tomeoftheeternalflow": "Tome of the Eternal Flow",
        "Tome of the Eternal Flow": "tomeoftheeternalflow",
        "toukaboushigure": "Toukabou Shigure",
        "Toukabou Shigure": "toukaboushigure",
        "travelershandysword": "Traveler's Handy Sword",
        "Traveler's Handy Sword": "travelershandysword",
        "tulaytullahsremembrance": "Tulaytullah's Remembrance",
        "Tulaytullah's Remembrance": "tulaytullahsremembrance",
        "twinnephrite": "Twin Nephrite",
        "Twin Nephrite": "twinnephrite",
        "ultimateoverlordsmegamagicsword": "\"Ultimate Overlord's Mega Magic Sword\"",
        "\"Ultimate Overlord's Mega Magic Sword\"": "ultimateoverlordsmegamagicsword",
        "urakumisugiri": "Uraku Misugiri",
        "Uraku Misugiri": "urakumisugiri",
        "verdict": "Verdict",
        "Verdict": "verdict",
        "vividnotions": "Vivid Notions",
        "Vivid Notions": "vividnotions",
        "vortexvanquisher": "Vortex Vanquisher",
        "Vortex Vanquisher": "vortexvanquisher",
        "wanderingevenstar": "Wandering Evenstar",
        "Wandering Evenstar": "wanderingevenstar",
        "wastergreatsword": "Waster Greatsword",
        "Waster Greatsword": "wastergreatsword",
        "wavebreakersfin": "Wavebreaker's Fin",
        "Wavebreaker's Fin": "wavebreakersfin",
        "waveridingwhirl": "Waveriding Whirl",
        "Waveriding Whirl": "waveridingwhirl",
        "whiteblind": "Whiteblind",
        "Whiteblind": "whiteblind",
        "whiteirongreatsword": "White Iron Greatsword",
        "White Iron Greatsword": "whiteirongreatsword",
        "whitetassel": "White Tassel",
        "White Tassel": "whitetassel",
        "windblumeode": "Windblume Ode",
        "Windblume Ode": "windblumeode",
        "wineandsong": "Wine and Song",
        "Wine and Song": "wineandsong",
        "wolffang": "Wolf-Fang",
        "Wolf-Fang": "wolffang",
        "wolfsgravestone": "Wolf's Gravestone",
        "Wolf's Gravestone": "wolfsgravestone",
        "xiphosmoonlight": "Xiphos' Moonlight",
        "Xiphos' Moonlight": "xiphosmoonlight"
    },
    "characters": {
        "albedo": "Albedo",
        "Albedo": "albedo",
        "alhaitham": "Alhaitham",
        "Alhaitham": "alhaitham",
        "aloy": "Aloy",
        "Aloy": "aloy",
        "amber": "Amber",
        "Amber": "amber",
        "arlecchino": "Arlecchino",
        "Arlecchino": "arlecchino",
        "ayaka": "Kamisato Ayaka",
        "Kamisato Ayaka": "ayaka",
        "ayato": "Kamisato Ayato",
        "Kamisato Ayato": "ayato",
        "baizhu": "Baizhu",
        "Baizhu": "baizhu",
        "barbara": "Barbara",
        "Barbara": "barbara",
        "beidou": "Beidou",
        "Beidou": "beidou",
        "bennett": "Bennett",
        "Bennett": "bennett",
        "candace": "Candace",
        "Candace": "candace",
        "charlotte": "Charlotte",
        "Charlotte": "charlotte",
        "chasca": "Chasca",
        "Chasca": "chasca",
        "chevreuse": "Chevreuse",
        "Chevreuse": "chevreuse",
        "chiori": "Chiori",
        "Chiori": "chiori",
        "chongyun": "Chongyun",
        "Chongyun": "chongyun",
        "citlali": "Citlali",
        "Citlali": "citlali",
        "clorinde": "Clorinde",
        "Clorinde": "clorinde",
        "collei": "Collei",
        "Collei": "collei",
        "cyno": "Cyno",
        "Cyno": "cyno",
        "dahlia": "Dahlia",
        "Dahlia": "dahlia",
        "dehya": "Dehya",
        "Dehya": "dehya",
        "diluc": "Diluc",
        "Diluc": "diluc",
        "diona": "Diona",
        "Diona": "diona",
        "dori": "Dori",
        "Dori": "dori",
        "emilie": "Emilie",
        "Emilie": "emilie",
        "escoffier": "Escoffier",
        "Escoffier": "escoffier",
        "eula": "Eula",
        "Eula": "eula",
        "faruzan": "Faruzan",
        "Faruzan": "faruzan",
        "fischl": "Fischl",
        "Fischl": "fischl",
        "freminet": "Freminet",
        "Freminet": "freminet",
        "furina": "Furina",
        "Furina": "furina",
        "gaming": "Gaming",
        "Gaming": "gaming",
        "ganyu": "Ganyu",
        "Ganyu": "ganyu",
        "gorou": "Gorou",
        "Gorou": "gorou",
        "heizou": "Shikanoin Heizou",
        "Shikanoin Heizou": "heizou",
        "hutao": "Hu Tao",
        "Hu Tao": "hutao",
        "itto": "Arataki Itto",
        "Arataki Itto": "itto",
        "jean": "Jean",
        "Jean": "jean",
        "kaeya": "Kaeya",
        "Kaeya": "kaeya",
        "kaveh": "Kaveh",
        "Kaveh": "kaveh",
        "kazuha": "Kaedehara Kazuha",
        "Kaedehara Kazuha": "kazuha",
        "keqing": "Keqing",
        "Keqing": "keqing",
        "kinich": "Kinich",
        "Kinich": "kinich",
        "kirara": "Kirara",
        "Kirara": "kirara",
        "klee": "Klee",
        "Klee": "klee",
        "kokomi": "Sangonomiya Kokomi",
        "Sangonomiya Kokomi": "kokomi",
        "kuki": "Kuki Shinobu",
        "Kuki Shinobu": "kuki",
        "lanyan": "Lan Yan",
        "Lan Yan": "lanyan",
        "layla": "Layla",
        "Layla": "layla",
        "lisa": "Lisa",
        "Lisa": "lisa",
        "lynette": "Lynette",
        "Lynette": "lynette",
        "lyney": "Lyney",
        "Lyney": "lyney",
        "mavuika": "Mavuika",
        "Mavuika": "mavuika",
        "mika": "Mika",
        "Mika": "mika",
        "mizuki": "Yumemizuki Mizuki",
        "Yumemizuki Mizuki": "mizuki",
        "mona": "Mona",
        "Mona": "mona",
        "mualani": "Mualani",
        "Mualani": "mualani",
        "nahida": "Nahida",
        "Nahida": "nahida",
        "navia": "Navia",
        "Navia": "navia",
        "neuvillette": "Neuvillette",
        "Neuvillette": "neuvillette",
        "nilou": "Nilou",
        "Nilou": "nilou",
        "ningguang": "Ningguang",
        "Ningguang": "ningguang",
        "noelle": "Noelle",
        "Noelle": "noelle",
        "ororon": "Ororon",
        "Ororon": "ororon",
        "qiqi": "Qiqi",
        "Qiqi": "qiqi",
        "raiden": "Raiden Shogun",
        "Raiden Shogun": "raiden",
        "razor": "Razor",
        "Razor": "razor",
        "rosaria": "Rosaria",
        "Rosaria": "rosaria",
        "sara": "Kujou Sara",
        "Kujou Sara": "sara",
        "sayu": "Sayu",
        "Sayu": "sayu",
        "sethos": "Sethos",
        "Sethos": "sethos",
        "shenhe": "Shenhe",
        "Shenhe": "shenhe",
        "sigewinne": "Sigewinne",
        "Sigewinne": "sigewinne",
        "skirk": "Skirk",
        "Skirk": "skirk",
        "sucrose": "Sucrose",
        "Sucrose": "sucrose",
        "tartaglia": "Tartaglia",
        "Tartaglia": "tartaglia",
        "thoma": "Thoma",
        "Thoma": "thoma",
        "tighnari": "Tighnari",
        "Tighnari": "tighnari",
        "traveleranemo": "Traveler (Anemo)",
        "Traveler (Anemo)": "traveleranemo",
        "travelerdendro": "Traveler (Dendro)",
        "Traveler (Dendro)": "travelerdendro",
        "travelerelectro": "Traveler (Electro)",
        "Traveler (Electro)": "travelerelectro",
        "travelergeo": "Traveler (Geo)",
        "Traveler (Geo)": "travelergeo",
        "travelerhydro": "Traveler (Hydro)",
        "Traveler (Hydro)": "travelerhydro",
        "travelerpyro": "Traveler (Pyro)",
        "Traveler (Pyro)": "travelerpyro",
        "varesa": "Varesa",
        "Varesa": "varesa",
        "venti": "Venti",
        "Venti": "venti",
        "wanderer": "Wanderer",
        "Wanderer": "wanderer",
        "wriothesley": "Wriothesley",
        "Wriothesley": "wriothesley",
        "xiangling": "Xiangling",
        "Xiangling": "xiangling",
        "xianyun": "Xianyun",
        "Xianyun": "xianyun",
        "xiao": "Xiao",
        "Xiao": "xiao",
        "xilonen": "Xilonen",
        "Xilonen": "xilonen",
        "xingqiu": "Xingqiu",
        "Xingqiu": "xingqiu",
        "xinyan": "Xinyan",
        "Xinyan": "xinyan",
        "yaemiko": "Yae Miko",
        "Yae Miko": "yaemiko",
        "yanfei": "Yanfei",
        "Yanfei": "yanfei",
        "yaoyao": "Yaoyao",
        "Yaoyao": "yaoyao",
        "yelan": "Yelan",
        "Yelan": "yelan",
        "yoimiya": "Yoimiya",
        "Yoimiya": "yoimiya",
        "yunjin": "Yun Jin",
        "Yun Jin": "yunjin",
        "zhongli": "Zhongli",
        "Zhongli": "zhongli"
    }
}